{
  "transitions": [
    "fade_in",
    "fade_out",
    "wipe_left",
    "wipe_right",
    "wipe_up",
    "wipe_down",
    "slash_left",
    "slash_right",
    "scale",
    "zoom_in",
    "zoom_out",
    "blur",
    "pixelate",
    "plus",
    "rotate",
    "circle_open",
    "circle_close",
    "diamond",
    "wedge",
    "push_left",
    "push_right",
    "push_up",
    "push_down",
    "morph"
  ],
  "text_intros": [
    "fade_in",
    "zoom_in",
    "slide_in_left",
    "slide_in_right",
    "slide_in_top",
    "slide_in_bottom",
    "bounce_in",
    "flip_in",
    "rotate_in",
    "typewriter",
    "scale_up",
    "spin_in"
  ],
  "text_outros": [
    "fade_out",
    "zoom_out",
    "slide_out_left",
    "slide_out_right",
    "slide_out_top",
    "slide_out_bottom",
    "bounce_out",
    "flip_out",
    "rotate_out",
    "scale_down",
    "spin_out"
  ],
  "video_intros": [
    "fade_in",
    "scale_up",
    "bounce_in",
    "flip_in",
    "rotate_in",
    "slide_in_left",
    "slide_in_right",
    "slide_in_top",
    "slide_in_bottom",
    "zoom_in"
  ],
  "video_outros": [
    "fade_out",
    "scale_down",
    "bounce_out",
    "flip_out",
    "rotate_out",
    "slide_out_left",
    "slide_out_right",
    "slide_out_top",
    "slide_out_bottom",
    "zoom_out"
  ],
  "masks": [
    "circle",
    "rect",
    "linear",
    "radial",
    "heart",
    "star",
    "diamond",
    "rounded_rect",
    "triangle",
    "hexagon"
  ],
  "text_loops": [
    "blink",
    "swing",
    "bounce",
    "pulse",
    "glow",
    "shake",
    "wave",
    "rotate",
    "scale",
    "skew"
  ],
  "transitions_real": [
    "Anti-CW Swirl",
    "Axis Rotation",
    "B&W Flash",
    "Black Fade",
    "Black smoke",
    "Blanch",
    "Blink",
    "Blocks",
    "Blue Lines",
    "Blur",
    "Blurred Highlight",
    "Bottom Left II",
    "Burn",
    "CW Swirl",
    "Camera Glow",
    "Cartoon Swirl",
    "Circular Slices II",
    "Clock wipe",
    "Cloud",
    "Color Glitch",
    "Color Swirl",
    "Cube",
    "Curling Wave",
    "Cutout Flip",
    "Diagonal Slices",
    "Dissolve",
    "Dissolve II",
    "Dissolve III",
    "Distortion",
    "Dots Right",
    "Flame",
    "Flash",
    "Flip",
    "Flip II",
    "Fold Over",
    "Glitch",
    "Gradient Wipe",
    "Horizontal Blur",
    "Horizontal Lines",
    "Horizontal Slice",
    "Inhale",
    "Left",
    "Light Beam",
    "Light Sweep II",
    "Lightning",
    "Like",
    "Little Devil",
    "Mix",
    "Montage Snippets",
    "Mosaic",
    "Open",
    "Open Horizontally",
    "Open Vertically",
    "Page Turning",
    "Particles",
    "Pull Out",
    "Pull in",
    "RGB Glitch",
    "Radial Blur",
    "Rainbow Filter",
    "Rainbow Warp",
    "Recorder",
    "Right",
    "Rotate CCW II",
    "Rotate CW II",
    "Shake 3",
    "Shutter",
    "Shutter II",
    "Slide",
    "Snow",
    "Split",
    "Split III",
    "Split IV",
    "Squeeze",
    "Stretch",
    "Stretch Left",
    "Stretch Right",
    "Stretch ll",
    "Strobe",
    "Super Like",
    "Switch",
    "Then and Now",
    "Transform Shimmer",
    "Twinkle Zoom",
    "Up",
    "Urban Glitch",
    "Vertical Blur",
    "Vertical Blur II",
    "Vertical Slices",
    "Vintage Screening",
    "Wave Left",
    "Wave Right",
    "Whirlpool",
    "White Flash",
    "White Ink",
    "White smoke",
    "Windmill",
    "Wipe Left",
    "Wipe Right",
    "Wipe Up",
    "Woosh"
  ],
  "transitions_count": 101,
  "note": "transitions_real là danh sách THỰC TỂ từ CapCut API"
}